{
  "headers": {
    "content-security-policy": "default-src 'none'; style-src 'unsafe-inline'; sandbox",
    "date": "Fri, 02 Sep 2022 08:04:29 GMT",
    "cache-control": "public, max-age=31536000, immutable",
    "x-amz-version-id": "_Emk_1O9vv6cZ1cZFthOhQ9pZI5hyBMY",
    "content-length": "5948",
    "x-amz-cf-pop": "ORD58-P3",
    "x-amz-replication-status": "FAILED",
    "x-amz-cf-id": "zcfPjcEjf4lvgRd9a6nrqTcWZbY7y5_xuYJVOlkZ0QscSSj5JhcUFA==",
    "accept-ranges": "bytes",
    "via": "1.1 0db70412184345548fe67fbd1d8e6d08.cloudfront.net (CloudFront)",
    "access-control-allow-origin": "*",
    "vary": "Accept-Encoding, Origin",
    "content-type": "application/typescript; charset=utf-8",
    "x-cache": "Hit from cloudfront",
    "last-modified": "Sun, 29 May 2022 16:28:42 GMT",
    "etag": "\"3528fc9ddd566c4d08bf8402adbdae82\"",
    "server": "deno/us-central1-b",
    "age": "1202080"
  },
  "url": "https://deno.land/x/discordeno@13.0.0-rc45/helpers/interactions/sendInteractionResponse.ts",
  "now": {
    "secs_since_epoch": 1663307948,
    "nanos_since_epoch": 604518924
  }
}